chutil/__init__.py
chutil/visualize/__init__.py
chutil/visualize/show.py
chutil-0.1.4.dist-info/DESCRIPTION.rst
chutil-0.1.4.dist-info/METADATA
chutil-0.1.4.dist-info/RECORD
chutil-0.1.4.dist-info/WHEEL
chutil-0.1.4.dist-info/metadata.json
chutil-0.1.4.dist-info/top_level.txt
