Metadata-Version: 2.0
Name: chutil
Version: 0.1.4
Summary: Chainer Utilities
Home-page: https://github.com/keisuke-umezawa/chutil.git
Author: keisuke umezawa
Author-email: keisuke.umezawa@gmail.com
License: MIT
Platform: UNKNOWN
